sayrex_bsuir_semester7_mzi/__init__.py
sayrex_bsuir_semester7_mzi/lab4.py
sayrex_bsuir_semester7_mzi/lab5.py
sayrex_bsuir_semester7_mzi/lab6.py
sayrex_bsuir_semester7_mzi-0.1.5.dist-info/METADATA
sayrex_bsuir_semester7_mzi-0.1.5.dist-info/WHEEL
sayrex_bsuir_semester7_mzi-0.1.5.dist-info/top_level.txt
sayrex_bsuir_semester7_mzi-0.1.5.dist-info/RECORD
