Metadata-Version: 2.4
Name: sayrex-bsuir-semester7-mzi
Version: 0.1.5
Summary: Лабораторные работы по МЗИ (7 семестр)
Author-email: sayrex <reshetneff2013@gmail.com>
License-Expression: MIT
Classifier: Programming Language :: Python :: 3
Classifier: Operating System :: OS Independent
Requires-Python: >=3.6
Requires-Dist: numpy
